mypackage/__init__.py
mypackage/__version__.py
mypackage/core.py
turiean/__init__.py
turiean/__version__.py
turiean/core.py
turiean-5.3.0.dist-info/LICENSE
turiean-5.3.0.dist-info/METADATA
turiean-5.3.0.dist-info/WHEEL
turiean-5.3.0.dist-info/top_level.txt
turiean-5.3.0.dist-info/RECORD
